connectapi.py
common/__init__.py
common/connectool.py
common/netmanager.py
connect/__init__.py
connect/conapi.py
connect/conbundle.py
connect/concertificate.py
connect/condevice.py
connect/conprofile.py
connect/conrequest.py
connect/contoken.py
connectcli-1.0.3.data/scripts/connectapi.py
connectcli-1.0.3.data/scripts/main.py
connectcli-1.0.3.dist-info/LICENSE
connectcli-1.0.3.dist-info/METADATA
connectcli-1.0.3.dist-info/WHEEL
connectcli-1.0.3.dist-info/entry_points.txt
connectcli-1.0.3.dist-info/top_level.txt
connectcli-1.0.3.dist-info/RECORD
