Metadata-Version: 2.1
Name: connectcli
Version: 1.0.3
Summary: app store connect api cli use apikey and issuer_id to authorize
Home-page: https://github.com/hepburnv/connectcli
Author: yuyuan yue
Author-email: last_yearv@163.com
License: MIT
Platform: UNKNOWN
Requires-Dist: Click
Requires-Dist: requests
Requires-Dist: authlib
